{
  "updated": "2025-12-28T04:57:55.476Z",
  "total": 48,
  "trends": [
    {
      "title": "www incometax gov in aadhaar pan link",
      "source": "Google Trends",
      "published": "Sat, 27 Dec 2025 20:20:00 -0800"
    },
    {
      "title": "rockets vs cavaliers",
      "source": "Google Trends",
      "published": "Sat, 27 Dec 2025 20:00:00 -0800"
    },
    {
      "title": "dhurandhar box office collection day 24",
      "source": "Google Trends",
      "published": "Sat, 27 Dec 2025 19:40:00 -0800"
    },
    {
      "title": "iphone fold",
      "source": "Google Trends",
      "published": "Sat, 27 Dec 2025 19:30:00 -0800"
    },
    {
      "title": "the copenhagen test",
      "source": "Google Trends",
      "published": "Sat, 27 Dec 2025 19:30:00 -0800"
    },
    {
      "title": "spurs vs jazz",
      "source": "Google Trends",
      "published": "Sat, 27 Dec 2025 19:20:00 -0800"
    },
    {
      "title": "nta ugc net",
      "source": "Google Trends",
      "published": "Sat, 27 Dec 2025 19:20:00 -0800"
    },
    {
      "title": "parasakthi",
      "source": "Google Trends",
      "published": "Sat, 27 Dec 2025 19:20:00 -0800"
    },
    {
      "title": "nabard",
      "source": "Google Trends",
      "published": "Sat, 27 Dec 2025 19:10:00 -0800"
    },
    {
      "title": "super smash",
      "source": "Google Trends",
      "published": "Sat, 27 Dec 2025 19:00:00 -0800"
    },
    {
      "title": "BREAKING| Supreme Court Takes Suo Motu Case On Aravalli Hills' Definition - Live Law",
      "source": "Google News",
      "published": "Sat, 27 Dec 2025 16:57:12 GMT"
    },
    {
      "title": "Myanmar’s military junta holds elections as civil war sparked by coup still rages - CNN",
      "source": "Google News",
      "published": "Sat, 27 Dec 2025 23:31:13 GMT"
    },
    {
      "title": "No fuel without PUCC, curbs on entry of non-BS6 vehicles to be permanent in Delhi, says Sirsa | India News - Hindustan Times",
      "source": "Google News",
      "published": "Sat, 27 Dec 2025 17:04:16 GMT"
    },
    {
      "title": "CBI moves Supreme Court against bail to Kuldeep Singh Sengar in Unnao Rape - Bar and Bench",
      "source": "Google News",
      "published": "Sat, 27 Dec 2025 04:52:32 GMT"
    },
    {
      "title": "As Russia strikes Kyiv, world leaders call for peace and support for Ukraine | World News - Hindustan Times",
      "source": "Google News",
      "published": "Sat, 27 Dec 2025 20:31:58 GMT"
    },
    {
      "title": "Congress to begin nationwide campaign against scrapping MGNREGA from January 5 - The Hindu",
      "source": "Google News",
      "published": "Sat, 27 Dec 2025 06:49:00 GMT"
    },
    {
      "title": "Bengaluru demolition brings K'taka CM Siddaramaiah, deputy DK Shivakumar on same page amid Congress unease | India News - Hindustan Times",
      "source": "Google News",
      "published": "Sun, 28 Dec 2025 03:32:20 GMT"
    },
    {
      "title": "Malaysian MPs Rally Behind Bangladeshi Hindus, Seek Visa Curbs After Lynching Incident - News18",
      "source": "Google News",
      "published": "Sat, 27 Dec 2025 10:02:59 GMT"
    },
    {
      "title": "30–35 terrorists on radar: Army steps up counterterror ops in J&amp;K; heightened vigilance amid 'Chillai Kal - The Times of India",
      "source": "Google News",
      "published": "Sun, 28 Dec 2025 03:29:00 GMT"
    },
    {
      "title": "Delhi Police apprehend 966 people in southeast Delhi ahead of New Year under Operation Aaghat 3.0 - The Hindu",
      "source": "Google News",
      "published": "Sat, 27 Dec 2025 09:53:00 GMT"
    },
    {
      "title": "Zelenskyy to meet Trump in US on Sunday: Is an end to Russia-Ukraine war close? - Firstpost",
      "source": "Google News",
      "published": "Sat, 27 Dec 2025 09:38:42 GMT"
    },
    {
      "title": "'If Ukraine did not want to resolve ...': Putin sends warning ahead of Trump-Zelenskyy meeting - The Times of India",
      "source": "Google News",
      "published": "Sat, 27 Dec 2025 22:47:00 GMT"
    },
    {
      "title": "'Fighting forest fires with garden hose': Canada physician says duty doctors should not be blamed for dea - The Times of India",
      "source": "Google News",
      "published": "Sat, 27 Dec 2025 14:08:00 GMT"
    },
    {
      "title": "Israel becomes first country to formally recognise Somaliland as independent state - The Hindu",
      "source": "Google News",
      "published": "Fri, 26 Dec 2025 21:12:00 GMT"
    },
    {
      "title": "UAE-India travel: Will airfares fall as 2 new airlines gain approval to operate? - Khaleej Times",
      "source": "Google News",
      "published": "Sat, 27 Dec 2025 02:00:00 GMT"
    },
    {
      "title": "Silver hits all-time high of Rs 2.42 lakh per kg in futures trade on supply fears, Fed rate cut bets - Moneycontrol",
      "source": "Google News",
      "published": "Sat, 27 Dec 2025 15:16:09 GMT"
    },
    {
      "title": "IndiGo fiasco: Key official removed, more action likely - The Times of India",
      "source": "Google News",
      "published": "Sat, 27 Dec 2025 21:27:00 GMT"
    },
    {
      "title": "Coforge to buy AI firm Encora for $2.35 billion in all-stock deal - Business Standard",
      "source": "Google News",
      "published": "Fri, 26 Dec 2025 15:41:52 GMT"
    },
    {
      "title": "Shaping 2025 in Minecraft - Minecraft",
      "source": "Google News",
      "published": "Sat, 27 Dec 2025 16:05:13 GMT"
    },
    {
      "title": "Pokémon GO Winter Weekend 2025 Event is Snow Much Fun - Pokemon.com",
      "source": "Google News",
      "published": "Sat, 27 Dec 2025 15:04:24 GMT"
    },
    {
      "title": "Nothing OS 4.0 arrives on CMF phones, bringing Android 16 and smarter features: All you need to know - livemint.com",
      "source": "Google News",
      "published": "Sat, 27 Dec 2025 02:08:43 GMT"
    },
    {
      "title": "Samsung Expands Its Audio Ecosystem for 2026 With Smarter Multi-Device Sound and Immersive New Designs - samsung.com",
      "source": "Google News",
      "published": "Sat, 27 Dec 2025 23:00:00 GMT"
    },
    {
      "title": "‘Dhurandhar’ box office collection day 23: Ranveer Singh, Akhshaye Khanna starrer crosses 1025 crore mark - The Times of India",
      "source": "Google News",
      "published": "Sun, 28 Dec 2025 00:29:00 GMT"
    },
    {
      "title": "Salman Khan dating history: Actor's relationships that made headlines- Aishwarya Rai, Katrina Kaif and more - WION",
      "source": "Google News",
      "published": "Sat, 27 Dec 2025 15:49:00 GMT"
    },
    {
      "title": "Jaideep Ahlawat replaces Akshaye Khanna in ‘Drishyam 3’; legal notice sent to ‘Dhurandhar’ star - The Hindu",
      "source": "Google News",
      "published": "Sat, 27 Dec 2025 11:47:00 GMT"
    },
    {
      "title": "'Na Main Tumhare Papa Se Darta, Na Bollywood Celebrity Se': Dhruv Rathee On Janhvi Kapoor Thumbnail - News18",
      "source": "Google News",
      "published": "Sun, 28 Dec 2025 02:00:04 GMT"
    },
    {
      "title": "England break 14-year drought with rare Ashes Test triumph - ICC",
      "source": "Google News",
      "published": "Sat, 27 Dec 2025 06:28:05 GMT"
    },
    {
      "title": "Ayush Mhatre to lead India at Under-19 World Cup - ESPNcricinfo",
      "source": "Google News",
      "published": "Sat, 27 Dec 2025 15:46:08 GMT"
    },
    {
      "title": "On Reports Of BCCI Meeting India Great VVS Laxman For Head Coach Post, Big Details Emerge - NDTV Sports",
      "source": "Google News",
      "published": "Sun, 28 Dec 2025 02:24:02 GMT"
    },
    {
      "title": "Premier League as-it-happened: Chelsea fell to Villa in Champions League race - ESPN India",
      "source": "Google News",
      "published": "Sat, 27 Dec 2025 16:57:46 GMT"
    },
    {
      "title": "Stunning James Webb Space Telescope Images of 2025 - ABC News",
      "source": "Google News",
      "published": "Sat, 27 Dec 2025 21:40:43 GMT"
    },
    {
      "title": "When the inner wall fell: complex hydrocarbon molecules in a young stellar disk - DST",
      "source": "Google News",
      "published": "Fri, 26 Dec 2025 12:44:34 GMT"
    },
    {
      "title": "Integrating Atmospheric Physics and Spatiotemporal Machine Learning to Project Wildfire Smoke Exposure and Health Risks in Canada under Future Climate - ESS Open Archive",
      "source": "Google News",
      "published": "Fri, 26 Dec 2025 20:06:07 GMT"
    },
    {
      "title": "Evaluating hydrogen displacement in sandstones: a comparative study of pore-network modelling and pore-scale visualisation experiments - ESS Open Archive",
      "source": "Google News",
      "published": "Fri, 26 Dec 2025 20:01:00 GMT"
    },
    {
      "title": "Indian vaccine maker seeks review of Australian alert on counterfeit rabies shots - Telegraph India",
      "source": "Google News",
      "published": "Sun, 28 Dec 2025 01:22:38 GMT"
    },
    {
      "title": "Steroid use is 'exploding' in Australia - but there are no clinical guidelines on how to quit - RNZ",
      "source": "Google News",
      "published": "Sun, 28 Dec 2025 02:46:35 GMT"
    },
    {
      "title": "New Atlas Reveals Glioma’s Hidden Complexity - EMJ",
      "source": "Google News",
      "published": "Sat, 27 Dec 2025 15:04:09 GMT"
    },
    {
      "title": "Not Getting Enough Sunlight? These 11 Foods Are Rich in Vitamin D - CNET",
      "source": "Google News",
      "published": "Sat, 27 Dec 2025 12:42:00 GMT"
    }
  ]
}